{
  "162015": {
    "x": 831.0,
    "y": 785.0,
    "visible": true,
    "action": "air",
    "pred_action": "air"
  },
  "162016": {
    "x": 837.0,
    "y": 777.0,
    "visible": true,
    "action": "air",
    "pred_action": "air"
  },
  "162017": {
    "x": 844.0,
    "y": 768.0,
    "visible": true,
    "action": "air",
    "pred_action": "air"
  },
  "162018": {
    "x": 848.0,
    "y": 761.0,
    "visible": true,
    "action": "air",
    "pred_action": "air"
  },
  "162019": {
    "x": 853.0,
    "y": 748.0,
    "visible": true,
    "action": "air",
    "pred_action": "air"
  },
  "162020": {
    "x": 857.0,
    "y": 736.0,
    "visible": true,
    "action": "air",
    "pred_action": "air"
  },
  "162021": {
    "x": 857.0,
    "y": 726.0,
    "visible": true,
    "action": "air",
    "pred_action": "air"
  },
  "162022": {
    "x": 858.0,
    "y": 713.0,
    "visible": true,
    "action": "air",
    "pred_action": "air"
  },
  "162023": {
    "x": 859.0,
    "y": 693.0,
    "visible": true,
    "action": "air",
    "pred_action": "air"
  },
  "162024": {
    "x": 856.0,
    "y": 688.0,
    "visible": true,
    "action": "air",
    "pred_action": "air"
  },
  "162025": {
    "x": 853.0,
    "y": 677.0,
    "visible": true,
    "action": "air",
    "pred_action": "air"
  },
  "162026": {
    "x": 855.0,
    "y": 658.0,
    "visible": true,
    "action": "air",
    "pred_action": "air"
  },
  "162027": {
    "x": 854.0,
    "y": 649.0,
    "visible": true,
    "action": "air",
    "pred_action": "air"
  },
  "162028": {
    "x": 852.0,
    "y": 637.0,
    "visible": true,
    "action": "air",
    "pred_action": "air"
  },
  "162029": {
    "x": 851.0,
    "y": 626.0,
    "visible": true,
    "action": "air",
    "pred_action": "air"
  },
  "162030": {
    "x": 849.0,
    "y": 617.0,
    "visible": true,
    "action": "air",
    "pred_action": "air"
  },
  "162031": {
    "x": 849.0,
    "y": 606.0,
    "visible": true,
    "action": "air",
    "pred_action": "air"
  },
  "162032": {
    "x": 848.0,
    "y": 597.0,
    "visible": true,
    "action": "air",
    "pred_action": "air"
  },
  "162033": {
    "x": 846.0,
    "y": 589.0,
    "visible": true,
    "action": "air",
    "pred_action": "air"
  },
  "162034": {
    "x": 845.0,
    "y": 580.0,
    "visible": true,
    "action": "air",
    "pred_action": "air"
  },
  "162035": {
    "x": 844.0,
    "y": 573.0,
    "visible": true,
    "action": "air",
    "pred_action": "air"
  },
  "162036": {
    "x": 843.0,
    "y": 565.0,
    "visible": true,
    "action": "air",
    "pred_action": "air"
  },
  "162037": {
    "x": 842.0,
    "y": 557.0,
    "visible": true,
    "action": "air",
    "pred_action": "air"
  },
  "162038": {
    "x": 837.0,
    "y": 551.0,
    "visible": true,
    "action": "air",
    "pred_action": "air"
  },
  "162039": {
    "x": 836.0,
    "y": 546.0,
    "visible": true,
    "action": "air",
    "pred_action": "air"
  },
  "162040": {
    "x": 835.0,
    "y": 539.0,
    "visible": true,
    "action": "air",
    "pred_action": "air"
  },
  "162041": {
    "x": 834.0,
    "y": 534.0,
    "visible": true,
    "action": "air",
    "pred_action": "air"
  },
  "162042": {
    "x": 833.0,
    "y": 530.0,
    "visible": true,
    "action": "air",
    "pred_action": "air"
  },
  "162043": {
    "x": 832.0,
    "y": 526.0,
    "visible": true,
    "action": "air",
    "pred_action": "air"
  },
  "162044": {
    "x": 831.0,
    "y": 522.0,
    "visible": true,
    "action": "air",
    "pred_action": "air"
  },
  "162045": {
    "x": 831.0,
    "y": 518.0,
    "visible": true,
    "action": "air",
    "pred_action": "air"
  },
  "162046": {
    "x": 830.0,
    "y": 515.0,
    "visible": true,
    "action": "air",
    "pred_action": "air"
  },
  "162047": {
    "x": 828.0,
    "y": 513.0,
    "visible": true,
    "action": "air",
    "pred_action": "air"
  },
  "162048": {
    "x": 827.0,
    "y": 511.0,
    "visible": true,
    "action": "air",
    "pred_action": "air"
  },
  "162049": {
    "x": 827.0,
    "y": 509.0,
    "visible": true,
    "action": "air",
    "pred_action": "air"
  },
  "162050": {
    "x": 825.0,
    "y": 508.3333333333333,
    "visible": false,
    "action": "air",
    "pred_action": "air"
  },
  "162051": {
    "x": 823.0,
    "y": 507.6666666666667,
    "visible": false,
    "action": "air",
    "pred_action": "air"
  },
  "162052": {
    "x": 821.0,
    "y": 507.0,
    "visible": true,
    "action": "air",
    "pred_action": "air"
  },
  "162053": {
    "x": 818.0,
    "y": 507.0,
    "visible": true,
    "action": "air",
    "pred_action": "air"
  },
  "162054": {
    "x": 819.0,
    "y": 508.0,
    "visible": true,
    "action": "air",
    "pred_action": "air"
  },
  "162055": {
    "x": 817.5,
    "y": 511.0,
    "visible": false,
    "action": "air",
    "pred_action": "air"
  },
  "162056": {
    "x": 816.0,
    "y": 514.0,
    "visible": true,
    "action": "air",
    "pred_action": "air"
  },
  "162057": {
    "x": 816.0,
    "y": 513.0,
    "visible": true,
    "action": "air",
    "pred_action": "air"
  },
  "162058": {
    "x": 814.5,
    "y": 516.0,
    "visible": false,
    "action": "air",
    "pred_action": "air"
  },
  "162059": {
    "x": 813.0,
    "y": 519.0,
    "visible": true,
    "action": "air",
    "pred_action": "air"
  },
  "162060": {
    "x": 811.0,
    "y": 521.0,
    "visible": true,
    "action": "air",
    "pred_action": "air"
  },
  "162061": {
    "x": 808.5,
    "y": 525.5,
    "visible": false,
    "action": "air",
    "pred_action": "air"
  },
  "162062": {
    "x": 806.0,
    "y": 530.0,
    "visible": true,
    "action": "air",
    "pred_action": "hit"
  },
  "162063": {
    "x": 823.6089108910891,
    "y": 522.8168316831682,
    "visible": true,
    "action": "hit",
    "pred_action": "hit"
  },
  "162064": {
    "x": 862.0,
    "y": 513.0,
    "visible": true,
    "action": "air",
    "pred_action": "air"
  },
  "162065": {
    "x": 893.0,
    "y": 499.0,
    "visible": true,
    "action": "air",
    "pred_action": "air"
  },
  "162066": {
    "x": 921.0,
    "y": 490.0,
    "visible": true,
    "action": "air",
    "pred_action": "air"
  },
  "162067": {
    "x": 944.0,
    "y": 485.0,
    "visible": true,
    "action": "air",
    "pred_action": "air"
  },
  "162068": {
    "x": 972.0,
    "y": 476.0,
    "visible": true,
    "action": "air",
    "pred_action": "air"
  },
  "162069": {
    "x": 984.0,
    "y": 468.0,
    "visible": true,
    "action": "air",
    "pred_action": "air"
  },
  "162070": {
    "x": 1004.0,
    "y": 466.0,
    "visible": true,
    "action": "air",
    "pred_action": "air"
  },
  "162071": {
    "x": 1014.0,
    "y": 463.0,
    "visible": true,
    "action": "air",
    "pred_action": "air"
  },
  "162072": {
    "x": 1040.0,
    "y": 457.0,
    "visible": true,
    "action": "air",
    "pred_action": "air"
  },
  "162073": {
    "x": 1047.0,
    "y": 456.0,
    "visible": true,
    "action": "air",
    "pred_action": "air"
  },
  "162074": {
    "x": 1061.0,
    "y": 452.0,
    "visible": false,
    "action": "air",
    "pred_action": "air"
  },
  "162075": {
    "x": 1075.0,
    "y": 448.0,
    "visible": true,
    "action": "air",
    "pred_action": "air"
  },
  "162076": {
    "x": 1087.0,
    "y": 447.0,
    "visible": true,
    "action": "air",
    "pred_action": "air"
  },
  "162077": {
    "x": 1100.0,
    "y": 446.0,
    "visible": true,
    "action": "air",
    "pred_action": "air"
  },
  "162078": {
    "x": 1106.0,
    "y": 445.0,
    "visible": true,
    "action": "air",
    "pred_action": "air"
  },
  "162079": {
    "x": 1117.0,
    "y": 446.0,
    "visible": true,
    "action": "air",
    "pred_action": "air"
  },
  "162080": {
    "x": 1125.589108910891,
    "y": 443.60891089108895,
    "visible": true,
    "action": "bounce",
    "pred_action": "bounce"
  },
  "162081": {
    "x": 1131.0,
    "y": 423.0,
    "visible": true,
    "action": "air",
    "pred_action": "air"
  },
  "162082": {
    "x": 1135.0,
    "y": 412.0,
    "visible": true,
    "action": "air",
    "pred_action": "air"
  },
  "162083": {
    "x": 1144.0,
    "y": 388.0,
    "visible": true,
    "action": "air",
    "pred_action": "air"
  },
  "162084": {
    "x": 1149.0,
    "y": 376.0,
    "visible": true,
    "action": "air",
    "pred_action": "air"
  },
  "162085": {
    "x": 1155.0,
    "y": 364.0,
    "visible": true,
    "action": "air",
    "pred_action": "air"
  },
  "162086": {
    "x": 1162.0,
    "y": 348.0,
    "visible": true,
    "action": "air",
    "pred_action": "air"
  },
  "162087": {
    "x": 1166.0,
    "y": 336.0,
    "visible": true,
    "action": "air",
    "pred_action": "air"
  },
  "162088": {
    "x": 1175.0,
    "y": 323.0,
    "visible": true,
    "action": "air",
    "pred_action": "air"
  },
  "162089": {
    "x": 1178.6089108910892,
    "y": 314.8375337533753,
    "visible": false,
    "action": "air",
    "pred_action": "air"
  },
  "162090": {
    "x": 1182.2178217821781,
    "y": 306.6750675067506,
    "visible": false,
    "action": "air",
    "pred_action": "air"
  },
  "162091": {
    "x": 1185.8267326732673,
    "y": 298.5126012601259,
    "visible": false,
    "action": "air",
    "pred_action": "air"
  },
  "162092": {
    "x": 1189.4356435643565,
    "y": 290.35013501350124,
    "visible": false,
    "action": "air",
    "pred_action": "air"
  },
  "162093": {
    "x": 1193.0445544554455,
    "y": 282.1876687668765,
    "visible": false,
    "action": "air",
    "pred_action": "air"
  },
  "162094": {
    "x": 1196.6534653465346,
    "y": 274.0252025202518,
    "visible": false,
    "action": "air",
    "pred_action": "air"
  },
  "162095": {
    "x": 1200.2623762376236,
    "y": 265.86273627362715,
    "visible": false,
    "action": "air",
    "pred_action": "air"
  },
  "162096": {
    "x": 1203.8712871287128,
    "y": 257.70027002700243,
    "visible": false,
    "action": "air",
    "pred_action": "air"
  },
  "162097": {
    "x": 1207.480198019802,
    "y": 249.53780378037774,
    "visible": false,
    "action": "air",
    "pred_action": "air"
  },
  "162098": {
    "x": 1211.089108910891,
    "y": 241.37533753375305,
    "visible": false,
    "action": "air",
    "pred_action": "air"
  },
  "162099": {
    "x": 1214.69801980198,
    "y": 233.21287128712834,
    "visible": true,
    "action": "hit",
    "pred_action": "hit"
  },
  "162100": {
    "x": 1204.3898514851485,
    "y": 236.19513201320098,
    "visible": false,
    "action": "air",
    "pred_action": "air"
  },
  "162101": {
    "x": 1194.0816831683167,
    "y": 239.1773927392736,
    "visible": false,
    "action": "air",
    "pred_action": "air"
  },
  "162102": {
    "x": 1183.773514851485,
    "y": 242.15965346534625,
    "visible": false,
    "action": "air",
    "pred_action": "air"
  },
  "162103": {
    "x": 1173.4653465346535,
    "y": 245.1419141914189,
    "visible": false,
    "action": "air",
    "pred_action": "air"
  },
  "162104": {
    "x": 1163.1571782178216,
    "y": 248.12417491749153,
    "visible": false,
    "action": "air",
    "pred_action": "air"
  },
  "162105": {
    "x": 1152.84900990099,
    "y": 251.10643564356417,
    "visible": false,
    "action": "air",
    "pred_action": "air"
  },
  "162106": {
    "x": 1142.5408415841584,
    "y": 254.0886963696368,
    "visible": false,
    "action": "air",
    "pred_action": "air"
  },
  "162107": {
    "x": 1132.2326732673266,
    "y": 257.07095709570945,
    "visible": false,
    "action": "air",
    "pred_action": "air"
  },
  "162108": {
    "x": 1121.924504950495,
    "y": 260.0532178217821,
    "visible": false,
    "action": "air",
    "pred_action": "air"
  },
  "162109": {
    "x": 1111.6163366336634,
    "y": 263.0354785478547,
    "visible": false,
    "action": "air",
    "pred_action": "air"
  },
  "162110": {
    "x": 1101.3081683168316,
    "y": 266.01773927392736,
    "visible": false,
    "action": "air",
    "pred_action": "air"
  },
  "162111": {
    "x": 1091.0,
    "y": 269.0,
    "visible": true,
    "action": "air",
    "pred_action": "air"
  },
  "162112": {
    "x": 1077.0,
    "y": 275.0,
    "visible": true,
    "action": "air",
    "pred_action": "air"
  },
  "162113": {
    "x": 1069.0,
    "y": 280.0,
    "visible": true,
    "action": "air",
    "pred_action": "air"
  },
  "162114": {
    "x": 1060.0,
    "y": 287.0,
    "visible": true,
    "action": "air",
    "pred_action": "air"
  },
  "162115": {
    "x": 1045.0,
    "y": 294.0,
    "visible": true,
    "action": "air",
    "pred_action": "air"
  },
  "162116": {
    "x": 1036.0,
    "y": 297.0,
    "visible": true,
    "action": "air",
    "pred_action": "air"
  },
  "162117": {
    "x": 1026.0,
    "y": 304.0,
    "visible": true,
    "action": "air",
    "pred_action": "air"
  },
  "162118": {
    "x": 1012.0,
    "y": 313.0,
    "visible": true,
    "action": "air",
    "pred_action": "air"
  },
  "162119": {
    "x": 999.0,
    "y": 324.0,
    "visible": true,
    "action": "air",
    "pred_action": "air"
  },
  "162120": {
    "x": 992.0,
    "y": 331.0,
    "visible": true,
    "action": "air",
    "pred_action": "air"
  },
  "162121": {
    "x": 979.0,
    "y": 341.0,
    "visible": true,
    "action": "air",
    "pred_action": "air"
  },
  "162122": {
    "x": 966.0,
    "y": 350.0,
    "visible": true,
    "action": "air",
    "pred_action": "air"
  },
  "162123": {
    "x": 954.0,
    "y": 362.0,
    "visible": true,
    "action": "air",
    "pred_action": "air"
  },
  "162124": {
    "x": 942.0,
    "y": 371.0,
    "visible": true,
    "action": "air",
    "pred_action": "air"
  },
  "162125": {
    "x": 926.0,
    "y": 381.0,
    "visible": true,
    "action": "air",
    "pred_action": "air"
  },
  "162126": {
    "x": 920.0,
    "y": 390.0,
    "visible": true,
    "action": "air",
    "pred_action": "air"
  },
  "162127": {
    "x": 906.0,
    "y": 405.0,
    "visible": true,
    "action": "air",
    "pred_action": "air"
  },
  "162128": {
    "x": 893.0,
    "y": 418.0,
    "visible": true,
    "action": "air",
    "pred_action": "air"
  },
  "162129": {
    "x": 881.0,
    "y": 430.0,
    "visible": true,
    "action": "air",
    "pred_action": "air"
  },
  "162130": {
    "x": 864.0,
    "y": 445.0,
    "visible": true,
    "action": "air",
    "pred_action": "air"
  },
  "162131": {
    "x": 859.0,
    "y": 455.0,
    "visible": true,
    "action": "air",
    "pred_action": "air"
  },
  "162132": {
    "x": 845.0,
    "y": 471.0,
    "visible": true,
    "action": "air",
    "pred_action": "air"
  },
  "162133": {
    "x": 831.0,
    "y": 485.0,
    "visible": true,
    "action": "air",
    "pred_action": "air"
  },
  "162134": {
    "x": 818.0,
    "y": 501.0,
    "visible": true,
    "action": "air",
    "pred_action": "air"
  },
  "162135": {
    "x": 808.0,
    "y": 514.0,
    "visible": true,
    "action": "air",
    "pred_action": "air"
  },
  "162136": {
    "x": 791.0,
    "y": 534.0,
    "visible": true,
    "action": "air",
    "pred_action": "air"
  },
  "162137": {
    "x": 776.0,
    "y": 551.0,
    "visible": true,
    "action": "air",
    "pred_action": "air"
  },
  "162138": {
    "x": 768.0,
    "y": 566.0,
    "visible": true,
    "action": "air",
    "pred_action": "air"
  },
  "162139": {
    "x": 756.0,
    "y": 583.0,
    "visible": true,
    "action": "air",
    "pred_action": "air"
  },
  "162140": {
    "x": 739.0,
    "y": 606.0,
    "visible": true,
    "action": "air",
    "pred_action": "air"
  },
  "162141": {
    "x": 727.0,
    "y": 623.0,
    "visible": true,
    "action": "air",
    "pred_action": "air"
  },
  "162142": {
    "x": 713.0,
    "y": 641.0,
    "visible": true,
    "action": "air",
    "pred_action": "air"
  },
  "162143": {
    "x": 698.0,
    "y": 664.0,
    "visible": true,
    "action": "air",
    "pred_action": "air"
  },
  "162144": {
    "x": 694.8960396039603,
    "y": 665.1435643564355,
    "visible": true,
    "action": "bounce",
    "pred_action": "bounce"
  },
  "162145": {
    "x": 681.0,
    "y": 659.0,
    "visible": true,
    "action": "air",
    "pred_action": "air"
  },
  "162146": {
    "x": 671.0,
    "y": 656.0,
    "visible": true,
    "action": "air",
    "pred_action": "air"
  },
  "162147": {
    "x": 664.0,
    "y": 652.0,
    "visible": true,
    "action": "air",
    "pred_action": "air"
  },
  "162148": {
    "x": 651.0,
    "y": 647.0,
    "visible": true,
    "action": "air",
    "pred_action": "air"
  },
  "162149": {
    "x": 642.0,
    "y": 645.0,
    "visible": true,
    "action": "air",
    "pred_action": "air"
  },
  "162150": {
    "x": 634.0,
    "y": 642.0,
    "visible": true,
    "action": "air",
    "pred_action": "air"
  },
  "162151": {
    "x": 623.0,
    "y": 641.0,
    "visible": true,
    "action": "air",
    "pred_action": "air"
  },
  "162152": {
    "x": 612.0,
    "y": 638.0,
    "visible": true,
    "action": "air",
    "pred_action": "air"
  },
  "162153": {
    "x": 604.0,
    "y": 636.0,
    "visible": true,
    "action": "air",
    "pred_action": "air"
  },
  "162154": {
    "x": 590.0,
    "y": 635.0,
    "visible": true,
    "action": "air",
    "pred_action": "air"
  },
  "162155": {
    "x": 581.0,
    "y": 635.0,
    "visible": true,
    "action": "air",
    "pred_action": "air"
  },
  "162156": {
    "x": 573.0,
    "y": 634.0,
    "visible": true,
    "action": "air",
    "pred_action": "air"
  },
  "162157": {
    "x": 561.0,
    "y": 637.0,
    "visible": true,
    "action": "air",
    "pred_action": "air"
  },
  "162158": {
    "x": 549.0,
    "y": 636.0,
    "visible": true,
    "action": "air",
    "pred_action": "air"
  },
  "162159": {
    "x": 543.0,
    "y": 637.0,
    "visible": true,
    "action": "air",
    "pred_action": "air"
  },
  "162160": {
    "x": 529.0,
    "y": 641.0,
    "visible": true,
    "action": "air",
    "pred_action": "air"
  },
  "162161": {
    "x": 518.0,
    "y": 643.0,
    "visible": true,
    "action": "air",
    "pred_action": "air"
  },
  "162162": {
    "x": 507.0,
    "y": 644.0,
    "visible": true,
    "action": "air",
    "pred_action": "air"
  },
  "162163": {
    "x": 497.0,
    "y": 648.0,
    "visible": true,
    "action": "air",
    "pred_action": "air"
  },
  "162164": {
    "x": 484.0,
    "y": 653.0,
    "visible": true,
    "action": "air",
    "pred_action": "air"
  },
  "162165": {
    "x": 476.0,
    "y": 657.0,
    "visible": true,
    "action": "air",
    "pred_action": "air"
  },
  "162166": {
    "x": 461.0,
    "y": 664.0,
    "visible": true,
    "action": "air",
    "pred_action": "air"
  },
  "162167": {
    "x": 453.5594059405938,
    "y": 663.9059405940591,
    "visible": true,
    "action": "hit",
    "pred_action": "hit"
  },
  "162168": {
    "x": 486.66955445544534,
    "y": 642.4294554455444,
    "visible": false,
    "action": "air",
    "pred_action": "air"
  },
  "162169": {
    "x": 519.779702970297,
    "y": 620.9529702970295,
    "visible": false,
    "action": "air",
    "pred_action": "air"
  },
  "162170": {
    "x": 552.8898514851485,
    "y": 599.4764851485147,
    "visible": false,
    "action": "air",
    "pred_action": "air"
  },
  "162171": {
    "x": 586.0,
    "y": 578.0,
    "visible": true,
    "action": "air",
    "pred_action": "air"
  },
  "162172": {
    "x": 623.0,
    "y": 563.0,
    "visible": true,
    "action": "air",
    "pred_action": "air"
  },
  "162173": {
    "x": 660.5,
    "y": 542.5,
    "visible": false,
    "action": "air",
    "pred_action": "air"
  },
  "162174": {
    "x": 698.0,
    "y": 522.0,
    "visible": true,
    "action": "air",
    "pred_action": "air"
  },
  "162175": {
    "x": 713.0,
    "y": 513.0,
    "visible": true,
    "action": "air",
    "pred_action": "air"
  },
  "162176": {
    "x": 757.0,
    "y": 491.0,
    "visible": true,
    "action": "air",
    "pred_action": "air"
  },
  "162177": {
    "x": 774.0,
    "y": 481.0,
    "visible": true,
    "action": "air",
    "pred_action": "air"
  },
  "162178": {
    "x": 799.0,
    "y": 470.0,
    "visible": true,
    "action": "air",
    "pred_action": "air"
  },
  "162179": {
    "x": 823.0,
    "y": 459.0,
    "visible": true,
    "action": "air",
    "pred_action": "air"
  },
  "162180": {
    "x": 849.0,
    "y": 447.0,
    "visible": true,
    "action": "air",
    "pred_action": "air"
  },
  "162181": {
    "x": 864.0,
    "y": 440.0,
    "visible": true,
    "action": "air",
    "pred_action": "air"
  },
  "162182": {
    "x": 892.0,
    "y": 429.0,
    "visible": true,
    "action": "air",
    "pred_action": "air"
  },
  "162183": {
    "x": 907.0,
    "y": 423.0,
    "visible": true,
    "action": "air",
    "pred_action": "air"
  },
  "162184": {
    "x": 924.0,
    "y": 417.0,
    "visible": true,
    "action": "air",
    "pred_action": "air"
  },
  "162185": {
    "x": 947.0,
    "y": 409.0,
    "visible": true,
    "action": "air",
    "pred_action": "air"
  },
  "162186": {
    "x": 956.0,
    "y": 403.0,
    "visible": true,
    "action": "air",
    "pred_action": "air"
  },
  "162187": {
    "x": 980.0,
    "y": 398.0,
    "visible": true,
    "action": "air",
    "pred_action": "air"
  },
  "162188": {
    "x": 996.0,
    "y": 394.0,
    "visible": true,
    "action": "air",
    "pred_action": "air"
  },
  "162189": {
    "x": 1007.0,
    "y": 391.0,
    "visible": true,
    "action": "air",
    "pred_action": "air"
  },
  "162190": {
    "x": 1023.0,
    "y": 387.0,
    "visible": true,
    "action": "air",
    "pred_action": "air"
  },
  "162191": {
    "x": 1037.0,
    "y": 384.0,
    "visible": true,
    "action": "air",
    "pred_action": "air"
  },
  "162192": {
    "x": 1045.0,
    "y": 382.0,
    "visible": true,
    "action": "air",
    "pred_action": "air"
  },
  "162193": {
    "x": 1065.0,
    "y": 380.0,
    "visible": true,
    "action": "air",
    "pred_action": "air"
  },
  "162194": {
    "x": 1075.0,
    "y": 378.0,
    "visible": true,
    "action": "air",
    "pred_action": "air"
  },
  "162195": {
    "x": 1085.0,
    "y": 377.0,
    "visible": true,
    "action": "air",
    "pred_action": "air"
  },
  "162196": {
    "x": 1097.0,
    "y": 377.0,
    "visible": true,
    "action": "air",
    "pred_action": "air"
  },
  "162197": {
    "x": 1105.0,
    "y": 376.0,
    "visible": true,
    "action": "air",
    "pred_action": "air"
  },
  "162198": {
    "x": 1116.0,
    "y": 376.0,
    "visible": true,
    "action": "air",
    "pred_action": "air"
  },
  "162199": {
    "x": 1127.0,
    "y": 377.0,
    "visible": true,
    "action": "air",
    "pred_action": "air"
  },
  "162200": {
    "x": 1135.0,
    "y": 377.0,
    "visible": true,
    "action": "air",
    "pred_action": "air"
  },
  "162201": {
    "x": 1145.0,
    "y": 377.0,
    "visible": true,
    "action": "air",
    "pred_action": "air"
  },
  "162202": {
    "x": 1154.0544554455446,
    "y": 375.53960396039565,
    "visible": true,
    "action": "bounce",
    "pred_action": "bounce"
  },
  "162203": {
    "x": 1161.0,
    "y": 371.0,
    "visible": true,
    "action": "air",
    "pred_action": "air"
  },
  "162204": {
    "x": 1164.0,
    "y": 361.0,
    "visible": true,
    "action": "air",
    "pred_action": "air"
  },
  "162205": {
    "x": 1173.0,
    "y": 353.0,
    "visible": true,
    "action": "air",
    "pred_action": "air"
  },
  "162206": {
    "x": 1178.0,
    "y": 344.0,
    "visible": true,
    "action": "air",
    "pred_action": "air"
  },
  "162207": {
    "x": 1183.0,
    "y": 333.0,
    "visible": true,
    "action": "air",
    "pred_action": "air"
  },
  "162208": {
    "x": 1190.0,
    "y": 326.0,
    "visible": true,
    "action": "air",
    "pred_action": "air"
  },
  "162209": {
    "x": 1194.0,
    "y": 316.0,
    "visible": true,
    "action": "air",
    "pred_action": "air"
  },
  "162210": {
    "x": 1198.8452145214521,
    "y": 311.47095709570954,
    "visible": false,
    "action": "air",
    "pred_action": "air"
  },
  "162211": {
    "x": 1203.6904290429043,
    "y": 306.94191419141913,
    "visible": false,
    "action": "air",
    "pred_action": "air"
  },
  "162212": {
    "x": 1208.5356435643564,
    "y": 302.41287128712867,
    "visible": false,
    "action": "air",
    "pred_action": "air"
  },
  "162213": {
    "x": 1213.3808580858085,
    "y": 297.8838283828382,
    "visible": false,
    "action": "air",
    "pred_action": "air"
  },
  "162214": {
    "x": 1218.2260726072607,
    "y": 293.35478547854774,
    "visible": false,
    "action": "air",
    "pred_action": "air"
  },
  "162215": {
    "x": 1223.0712871287128,
    "y": 288.82574257425733,
    "visible": false,
    "action": "air",
    "pred_action": "air"
  },
  "162216": {
    "x": 1227.916501650165,
    "y": 284.29669966996687,
    "visible": false,
    "action": "air",
    "pred_action": "air"
  },
  "162217": {
    "x": 1232.7617161716173,
    "y": 279.7676567656764,
    "visible": false,
    "action": "air",
    "pred_action": "air"
  },
  "162218": {
    "x": 1237.6069306930694,
    "y": 275.23861386138594,
    "visible": false,
    "action": "air",
    "pred_action": "air"
  },
  "162219": {
    "x": 1242.4521452145216,
    "y": 270.70957095709554,
    "visible": false,
    "action": "air",
    "pred_action": "air"
  },
  "162220": {
    "x": 1247.2973597359737,
    "y": 266.1805280528051,
    "visible": false,
    "action": "air",
    "pred_action": "air"
  },
  "162221": {
    "x": 1252.1425742574258,
    "y": 261.6514851485146,
    "visible": false,
    "action": "air",
    "pred_action": "air"
  },
  "162222": {
    "x": 1256.987788778878,
    "y": 257.1224422442242,
    "visible": false,
    "action": "air",
    "pred_action": "air"
  },
  "162223": {
    "x": 1261.8330033003301,
    "y": 252.59339933993374,
    "visible": false,
    "action": "air",
    "pred_action": "air"
  },
  "162224": {
    "x": 1266.6782178217823,
    "y": 248.06435643564328,
    "visible": true,
    "action": "hit",
    "pred_action": "hit"
  },
  "162225": {
    "x": 1258.0383663366338,
    "y": 250.55899339933967,
    "visible": false,
    "action": "air",
    "pred_action": "air"
  },
  "162226": {
    "x": 1249.3985148514853,
    "y": 253.05363036303606,
    "visible": false,
    "action": "air",
    "pred_action": "air"
  },
  "162227": {
    "x": 1240.7586633663368,
    "y": 255.54826732673246,
    "visible": false,
    "action": "air",
    "pred_action": "air"
  },
  "162228": {
    "x": 1232.118811881188,
    "y": 258.04290429042885,
    "visible": false,
    "action": "air",
    "pred_action": "air"
  },
  "162229": {
    "x": 1223.4789603960396,
    "y": 260.53754125412524,
    "visible": false,
    "action": "air",
    "pred_action": "air"
  },
  "162230": {
    "x": 1214.8391089108911,
    "y": 263.03217821782164,
    "visible": false,
    "action": "air",
    "pred_action": "air"
  },
  "162231": {
    "x": 1206.1992574257426,
    "y": 265.52681518151803,
    "visible": false,
    "action": "air",
    "pred_action": "air"
  },
  "162232": {
    "x": 1197.5594059405942,
    "y": 268.0214521452144,
    "visible": false,
    "action": "air",
    "pred_action": "air"
  },
  "162233": {
    "x": 1188.9195544554455,
    "y": 270.5160891089108,
    "visible": false,
    "action": "air",
    "pred_action": "air"
  },
  "162234": {
    "x": 1180.279702970297,
    "y": 273.0107260726072,
    "visible": false,
    "action": "air",
    "pred_action": "air"
  },
  "162235": {
    "x": 1171.6398514851485,
    "y": 275.5053630363036,
    "visible": false,
    "action": "air",
    "pred_action": "air"
  },
  "162236": {
    "x": 1163.0,
    "y": 278.0,
    "visible": true,
    "action": "air",
    "pred_action": "air"
  },
  "162237": {
    "x": 1157.0,
    "y": 281.0,
    "visible": true,
    "action": "air",
    "pred_action": "air"
  },
  "162238": {
    "x": 1146.0,
    "y": 288.0,
    "visible": true,
    "action": "air",
    "pred_action": "air"
  },
  "162239": {
    "x": 1134.0,
    "y": 292.0,
    "visible": true,
    "action": "air",
    "pred_action": "air"
  },
  "162240": {
    "x": 1129.0,
    "y": 297.0,
    "visible": true,
    "action": "air",
    "pred_action": "air"
  },
  "162241": {
    "x": 1117.0,
    "y": 304.0,
    "visible": true,
    "action": "air",
    "pred_action": "air"
  },
  "162242": {
    "x": 1105.0,
    "y": 310.0,
    "visible": true,
    "action": "air",
    "pred_action": "air"
  },
  "162243": {
    "x": 1098.0,
    "y": 317.0,
    "visible": true,
    "action": "air",
    "pred_action": "air"
  },
  "162244": {
    "x": 1087.0,
    "y": 325.0,
    "visible": true,
    "action": "air",
    "pred_action": "air"
  },
  "162245": {
    "x": 1074.0,
    "y": 332.0,
    "visible": true,
    "action": "air",
    "pred_action": "air"
  },
  "162246": {
    "x": 1067.0,
    "y": 339.0,
    "visible": true,
    "action": "air",
    "pred_action": "air"
  },
  "162247": {
    "x": 1056.0,
    "y": 348.0,
    "visible": true,
    "action": "air",
    "pred_action": "air"
  },
  "162248": {
    "x": 1044.0,
    "y": 357.0,
    "visible": true,
    "action": "air",
    "pred_action": "air"
  },
  "162249": {
    "x": 1037.0,
    "y": 366.0,
    "visible": true,
    "action": "air",
    "pred_action": "air"
  },
  "162250": {
    "x": 1025.0,
    "y": 377.0,
    "visible": true,
    "action": "air",
    "pred_action": "air"
  },
  "162251": {
    "x": 1012.0,
    "y": 388.0,
    "visible": true,
    "action": "air",
    "pred_action": "air"
  },
  "162252": {
    "x": 1003.0,
    "y": 396.0,
    "visible": true,
    "action": "air",
    "pred_action": "air"
  },
  "162253": {
    "x": 993.0,
    "y": 411.0,
    "visible": true,
    "action": "air",
    "pred_action": "air"
  },
  "162254": {
    "x": 979.0,
    "y": 423.0,
    "visible": true,
    "action": "air",
    "pred_action": "air"
  },
  "162255": {
    "x": 970.0,
    "y": 435.0,
    "visible": true,
    "action": "air",
    "pred_action": "air"
  },
  "162256": {
    "x": 954.0,
    "y": 454.0,
    "visible": true,
    "action": "air",
    "pred_action": "air"
  },
  "162257": {
    "x": 944.0,
    "y": 466.0,
    "visible": true,
    "action": "air",
    "pred_action": "air"
  },
  "162258": {
    "x": 934.0,
    "y": 476.0,
    "visible": true,
    "action": "air",
    "pred_action": "air"
  },
  "162259": {
    "x": 922.0,
    "y": 490.0,
    "visible": true,
    "action": "air",
    "pred_action": "air"
  },
  "162260": {
    "x": 910.0,
    "y": 506.0,
    "visible": true,
    "action": "air",
    "pred_action": "air"
  },
  "162261": {
    "x": 897.0,
    "y": 521.0,
    "visible": true,
    "action": "air",
    "pred_action": "air"
  },
  "162262": {
    "x": 888.0,
    "y": 536.0,
    "visible": true,
    "action": "air",
    "pred_action": "air"
  },
  "162263": {
    "x": 873.0,
    "y": 557.0,
    "visible": true,
    "action": "air",
    "pred_action": "air"
  },
  "162264": {
    "x": 862.0,
    "y": 574.0,
    "visible": true,
    "action": "air",
    "pred_action": "air"
  },
  "162265": {
    "x": 850.0,
    "y": 590.0,
    "visible": true,
    "action": "air",
    "pred_action": "air"
  },
  "162266": {
    "x": 833.0,
    "y": 614.0,
    "visible": true,
    "action": "air",
    "pred_action": "air"
  },
  "162267": {
    "x": 822.0,
    "y": 631.0,
    "visible": true,
    "action": "air",
    "pred_action": "air"
  },
  "162268": {
    "x": 806.0,
    "y": 651.0,
    "visible": true,
    "action": "air",
    "pred_action": "air"
  },
  "162269": {
    "x": 793.0,
    "y": 676.0,
    "visible": true,
    "action": "air",
    "pred_action": "air"
  },
  "162270": {
    "x": 783.0,
    "y": 694.0,
    "visible": true,
    "action": "air",
    "pred_action": "air"
  },
  "162271": {
    "x": 769.0,
    "y": 714.0,
    "visible": true,
    "action": "air",
    "pred_action": "air"
  },
  "162272": {
    "x": 753.0,
    "y": 742.0,
    "visible": true,
    "action": "air",
    "pred_action": "air"
  },
  "162273": {
    "x": 739.0,
    "y": 765.0,
    "visible": true,
    "action": "air",
    "pred_action": "air"
  },
  "162274": {
    "x": 729.0,
    "y": 785.0,
    "visible": true,
    "action": "air",
    "pred_action": "air"
  },
  "162275": {
    "x": 715.1567656765676,
    "y": 807.3415841584158,
    "visible": false,
    "action": "air",
    "pred_action": "air"
  },
  "162276": {
    "x": 701.3135313531353,
    "y": 829.6831683168316,
    "visible": false,
    "action": "air",
    "pred_action": "air"
  },
  "162277": {
    "x": 687.4702970297029,
    "y": 852.0247524752474,
    "visible": true,
    "action": "bounce",
    "pred_action": "bounce"
  },
  "162278": {
    "x": 676.8267326732672,
    "y": 851.7772277227721,
    "visible": false,
    "action": "air",
    "pred_action": "air"
  },
  "162279": {
    "x": 666.1831683168316,
    "y": 851.5297029702969,
    "visible": false,
    "action": "air",
    "pred_action": "air"
  },
  "162280": {
    "x": 655.5396039603959,
    "y": 851.2821782178215,
    "visible": false,
    "action": "air",
    "pred_action": "air"
  },
  "162281": {
    "x": 644.8960396039603,
    "y": 851.0346534653463,
    "visible": false,
    "action": "air",
    "pred_action": "air"
  },
  "162282": {
    "x": 634.2524752475246,
    "y": 850.787128712871,
    "visible": true,
    "action": "hit",
    "pred_action": "hit"
  },
  "162283": {
    "x": 651.8349834983497,
    "y": 815.8580858085807,
    "visible": false,
    "action": "air",
    "pred_action": "air"
  },
  "162284": {
    "x": 669.4174917491748,
    "y": 780.9290429042903,
    "visible": false,
    "action": "air",
    "pred_action": "air"
  },
  "162285": {
    "x": 687.0,
    "y": 746.0,
    "visible": true,
    "action": "air",
    "pred_action": "air"
  },
  "162286": {
    "x": 700.0,
    "y": 729.0,
    "visible": true,
    "action": "air",
    "pred_action": "air"
  },
  "162287": {
    "x": 715.0,
    "y": 695.0,
    "visible": true,
    "action": "air",
    "pred_action": "air"
  },
  "162288": {
    "x": 735.0,
    "y": 667.0,
    "visible": true,
    "action": "air",
    "pred_action": "air"
  },
  "162289": {
    "x": 744.0,
    "y": 647.0,
    "visible": true,
    "action": "air",
    "pred_action": "air"
  },
  "162290": {
    "x": 760.0,
    "y": 622.0,
    "visible": true,
    "action": "air",
    "pred_action": "air"
  },
  "162291": {
    "x": 772.0,
    "y": 601.0,
    "visible": true,
    "action": "air",
    "pred_action": "air"
  },
  "162292": {
    "x": 786.0,
    "y": 582.0,
    "visible": true,
    "action": "air",
    "pred_action": "air"
  },
  "162293": {
    "x": 796.0,
    "y": 563.0,
    "visible": true,
    "action": "air",
    "pred_action": "air"
  },
  "162294": {
    "x": 806.0,
    "y": 547.0,
    "visible": true,
    "action": "air",
    "pred_action": "air"
  },
  "162295": {
    "x": 818.0,
    "y": 531.0,
    "visible": true,
    "action": "air",
    "pred_action": "air"
  },
  "162296": {
    "x": 828.0,
    "y": 515.0,
    "visible": true,
    "action": "air",
    "pred_action": "air"
  },
  "162297": {
    "x": 835.0,
    "y": 503.0,
    "visible": true,
    "action": "air",
    "pred_action": "air"
  },
  "162298": {
    "x": 847.0,
    "y": 489.0,
    "visible": true,
    "action": "air",
    "pred_action": "air"
  },
  "162299": {
    "x": 855.0,
    "y": 475.0,
    "visible": true,
    "action": "air",
    "pred_action": "air"
  },
  "162300": {
    "x": 862.0,
    "y": 464.0,
    "visible": true,
    "action": "air",
    "pred_action": "air"
  },
  "162301": {
    "x": 874.0,
    "y": 455.0,
    "visible": true,
    "action": "air",
    "pred_action": "air"
  },
  "162302": {
    "x": 880.0,
    "y": 445.0,
    "visible": true,
    "action": "air",
    "pred_action": "air"
  },
  "162303": {
    "x": 888.0,
    "y": 434.0,
    "visible": true,
    "action": "air",
    "pred_action": "air"
  },
  "162304": {
    "x": 894.0,
    "y": 428.0,
    "visible": true,
    "action": "air",
    "pred_action": "air"
  },
  "162305": {
    "x": 902.0,
    "y": 418.0,
    "visible": true,
    "action": "air",
    "pred_action": "air"
  },
  "162306": {
    "x": 908.0,
    "y": 412.0,
    "visible": true,
    "action": "air",
    "pred_action": "air"
  },
  "162307": {
    "x": 915.0,
    "y": 405.0,
    "visible": true,
    "action": "air",
    "pred_action": "air"
  },
  "162308": {
    "x": 921.0,
    "y": 400.0,
    "visible": true,
    "action": "air",
    "pred_action": "air"
  },
  "162309": {
    "x": 926.0,
    "y": 393.0,
    "visible": true,
    "action": "air",
    "pred_action": "air"
  },
  "162310": {
    "x": 933.0,
    "y": 388.0,
    "visible": true,
    "action": "air",
    "pred_action": "air"
  },
  "162311": {
    "x": 939.0,
    "y": 385.0,
    "visible": true,
    "action": "air",
    "pred_action": "air"
  },
  "162312": {
    "x": 943.0,
    "y": 380.0,
    "visible": true,
    "action": "air",
    "pred_action": "air"
  },
  "162313": {
    "x": 949.0,
    "y": 377.0,
    "visible": true,
    "action": "air",
    "pred_action": "air"
  },
  "162314": {
    "x": 953.0,
    "y": 374.0,
    "visible": true,
    "action": "air",
    "pred_action": "air"
  },
  "162315": {
    "x": 956.0,
    "y": 371.0,
    "visible": true,
    "action": "air",
    "pred_action": "air"
  },
  "162316": {
    "x": 965.0,
    "y": 369.0,
    "visible": true,
    "action": "air",
    "pred_action": "air"
  },
  "162317": {
    "x": 969.0,
    "y": 366.0,
    "visible": true,
    "action": "air",
    "pred_action": "air"
  },
  "162318": {
    "x": 971.0,
    "y": 365.0,
    "visible": true,
    "action": "air",
    "pred_action": "air"
  },
  "162319": {
    "x": 976.0,
    "y": 364.0,
    "visible": true,
    "action": "air",
    "pred_action": "air"
  },
  "162320": {
    "x": 981.0,
    "y": 364.0,
    "visible": true,
    "action": "air",
    "pred_action": "air"
  },
  "162321": {
    "x": 983.0,
    "y": 362.0,
    "visible": true,
    "action": "air",
    "pred_action": "air"
  },
  "162322": {
    "x": 986.0,
    "y": 363.0,
    "visible": true,
    "action": "air",
    "pred_action": "air"
  },
  "162323": {
    "x": 994.0,
    "y": 364.0,
    "visible": true,
    "action": "air",
    "pred_action": "air"
  },
  "162324": {
    "x": 995.0,
    "y": 364.0,
    "visible": true,
    "action": "air",
    "pred_action": "air"
  },
  "162325": {
    "x": 999.0,
    "y": 365.0,
    "visible": true,
    "action": "air",
    "pred_action": "air"
  },
  "162326": {
    "x": 1003.0,
    "y": 366.0,
    "visible": true,
    "action": "air",
    "pred_action": "air"
  },
  "162327": {
    "x": 1004.0,
    "y": 366.0,
    "visible": true,
    "action": "air",
    "pred_action": "air"
  },
  "162328": {
    "x": 1009.0,
    "y": 368.0,
    "visible": true,
    "action": "air",
    "pred_action": "air"
  },
  "162329": {
    "x": 1013.0,
    "y": 371.0,
    "visible": true,
    "action": "air",
    "pred_action": "air"
  },
  "162330": {
    "x": 1013.0,
    "y": 373.0,
    "visible": true,
    "action": "air",
    "pred_action": "air"
  },
  "162331": {
    "x": 1015.0,
    "y": 375.0,
    "visible": true,
    "action": "air",
    "pred_action": "air"
  },
  "162332": {
    "x": 1022.0,
    "y": 377.0,
    "visible": true,
    "action": "air",
    "pred_action": "air"
  },
  "162333": {
    "x": 1021.6287128712869,
    "y": 379.25247524752444,
    "visible": true,
    "action": "bounce",
    "pred_action": "bounce"
  },
  "162334": {
    "x": 1025.0,
    "y": 368.0,
    "visible": true,
    "action": "air",
    "pred_action": "air"
  },
  "162335": {
    "x": 1028.0,
    "y": 358.0,
    "visible": true,
    "action": "air",
    "pred_action": "air"
  },
  "162336": {
    "x": 1029.0,
    "y": 350.0,
    "visible": true,
    "action": "air",
    "pred_action": "air"
  },
  "162337": {
    "x": 1032.0,
    "y": 344.0,
    "visible": true,
    "action": "air",
    "pred_action": "air"
  },
  "162338": {
    "x": 1033.0,
    "y": 335.0,
    "visible": true,
    "action": "air",
    "pred_action": "air"
  },
  "162339": {
    "x": 1036.0,
    "y": 331.0,
    "visible": true,
    "action": "air",
    "pred_action": "air"
  },
  "162340": {
    "x": 1038.0,
    "y": 324.0,
    "visible": true,
    "action": "air",
    "pred_action": "air"
  },
  "162341": {
    "x": 1040.0,
    "y": 315.0,
    "visible": true,
    "action": "air",
    "pred_action": "air"
  },
  "162342": {
    "x": 1041.0,
    "y": 308.0,
    "visible": true,
    "action": "air",
    "pred_action": "air"
  },
  "162343": {
    "x": 1043.0,
    "y": 303.0,
    "visible": true,
    "action": "air",
    "pred_action": "air"
  },
  "162344": {
    "x": 1046.0,
    "y": 297.0,
    "visible": true,
    "action": "air",
    "pred_action": "air"
  },
  "162345": {
    "x": 1046.0,
    "y": 295.0,
    "visible": true,
    "action": "air",
    "pred_action": "air"
  },
  "162346": {
    "x": 1046.0,
    "y": 291.0,
    "visible": true,
    "action": "air",
    "pred_action": "air"
  },
  "162347": {
    "x": 1054.0,
    "y": 284.0,
    "visible": true,
    "action": "air",
    "pred_action": "air"
  },
  "162348": {
    "x": 1054.8799504950493,
    "y": 280.27599009900985,
    "visible": false,
    "action": "air",
    "pred_action": "air"
  },
  "162349": {
    "x": 1055.759900990099,
    "y": 276.5519801980197,
    "visible": false,
    "action": "air",
    "pred_action": "air"
  },
  "162350": {
    "x": 1056.6398514851485,
    "y": 272.82797029702954,
    "visible": false,
    "action": "air",
    "pred_action": "air"
  },
  "162351": {
    "x": 1057.5198019801978,
    "y": 269.1039603960394,
    "visible": true,
    "action": "hit",
    "pred_action": "air"
  },
  "162352": {
    "x": 1052.0,
    "y": 267.0,
    "visible": true,
    "action": "air",
    "pred_action": "air"
  },
  "162353": {
    "x": 1045.0,
    "y": 266.0,
    "visible": true,
    "action": "air",
    "pred_action": "air"
  },
  "162354": {
    "x": 1042.0,
    "y": 264.0,
    "visible": true,
    "action": "air",
    "pred_action": "air"
  },
  "162355": {
    "x": 1038.0,
    "y": 263.0,
    "visible": true,
    "action": "air",
    "pred_action": "air"
  },
  "162356": {
    "x": 1032.0,
    "y": 260.0,
    "visible": true,
    "action": "air",
    "pred_action": "air"
  },
  "162357": {
    "x": 1029.0,
    "y": 258.0,
    "visible": true,
    "action": "air",
    "pred_action": "air"
  },
  "162358": {
    "x": 1025.0,
    "y": 257.0,
    "visible": true,
    "action": "air",
    "pred_action": "air"
  },
  "162359": {
    "x": 1016.0,
    "y": 255.0,
    "visible": true,
    "action": "air",
    "pred_action": "air"
  },
  "162360": {
    "x": 1014.0,
    "y": 252.0,
    "visible": true,
    "action": "air",
    "pred_action": "air"
  },
  "162361": {
    "x": 1010.0,
    "y": 252.0,
    "visible": true,
    "action": "air",
    "pred_action": "air"
  },
  "162362": {
    "x": 1003.0,
    "y": 251.0,
    "visible": true,
    "action": "air",
    "pred_action": "air"
  },
  "162363": {
    "x": 1001.0,
    "y": 251.0,
    "visible": true,
    "action": "air",
    "pred_action": "air"
  },
  "162364": {
    "x": 996.0,
    "y": 250.0,
    "visible": true,
    "action": "air",
    "pred_action": "air"
  },
  "162365": {
    "x": 987.0,
    "y": 249.0,
    "visible": true,
    "action": "air",
    "pred_action": "air"
  },
  "162366": {
    "x": 985.0,
    "y": 249.0,
    "visible": true,
    "action": "air",
    "pred_action": "air"
  },
  "162367": {
    "x": 980.0,
    "y": 249.0,
    "visible": true,
    "action": "air",
    "pred_action": "air"
  },
  "162368": {
    "x": 974.0,
    "y": 249.0,
    "visible": true,
    "action": "air",
    "pred_action": "air"
  },
  "162369": {
    "x": 971.0,
    "y": 250.0,
    "visible": true,
    "action": "air",
    "pred_action": "air"
  },
  "162370": {
    "x": 966.0,
    "y": 250.0,
    "visible": true,
    "action": "air",
    "pred_action": "air"
  },
  "162371": {
    "x": 963.0,
    "y": 251.0,
    "visible": true,
    "action": "air",
    "pred_action": "air"
  },
  "162372": {
    "x": 954.0,
    "y": 252.0,
    "visible": true,
    "action": "air",
    "pred_action": "air"
  },
  "162373": {
    "x": 950.0,
    "y": 254.0,
    "visible": true,
    "action": "air",
    "pred_action": "air"
  },
  "162374": {
    "x": 946.0,
    "y": 255.0,
    "visible": true,
    "action": "air",
    "pred_action": "air"
  },
  "162375": {
    "x": 940.0,
    "y": 257.0,
    "visible": true,
    "action": "air",
    "pred_action": "air"
  },
  "162376": {
    "x": 934.0,
    "y": 259.0,
    "visible": true,
    "action": "air",
    "pred_action": "air"
  },
  "162377": {
    "x": 926.0,
    "y": 261.0,
    "visible": true,
    "action": "air",
    "pred_action": "air"
  },
  "162378": {
    "x": 925.0,
    "y": 262.0,
    "visible": true,
    "action": "air",
    "pred_action": "air"
  },
  "162379": {
    "x": 918.0,
    "y": 268.0,
    "visible": true,
    "action": "air",
    "pred_action": "air"
  },
  "162380": {
    "x": 913.0,
    "y": 268.0,
    "visible": true,
    "action": "air",
    "pred_action": "air"
  },
  "162381": {
    "x": 908.0,
    "y": 272.0,
    "visible": true,
    "action": "air",
    "pred_action": "air"
  },
  "162382": {
    "x": 904.0,
    "y": 275.0,
    "visible": true,
    "action": "air",
    "pred_action": "air"
  },
  "162383": {
    "x": 895.0,
    "y": 279.0,
    "visible": true,
    "action": "air",
    "pred_action": "air"
  },
  "162384": {
    "x": 890.0,
    "y": 284.0,
    "visible": true,
    "action": "air",
    "pred_action": "air"
  },
  "162385": {
    "x": 887.0,
    "y": 287.0,
    "visible": true,
    "action": "air",
    "pred_action": "air"
  },
  "162386": {
    "x": 880.0,
    "y": 291.0,
    "visible": true,
    "action": "air",
    "pred_action": "air"
  },
  "162387": {
    "x": 874.0,
    "y": 296.0,
    "visible": true,
    "action": "air",
    "pred_action": "air"
  },
  "162388": {
    "x": 866.0,
    "y": 301.0,
    "visible": true,
    "action": "air",
    "pred_action": "air"
  },
  "162389": {
    "x": 862.0,
    "y": 306.0,
    "visible": true,
    "action": "air",
    "pred_action": "air"
  },
  "162390": {
    "x": 857.0,
    "y": 311.0,
    "visible": true,
    "action": "air",
    "pred_action": "air"
  },
  "162391": {
    "x": 852.0,
    "y": 318.0,
    "visible": true,
    "action": "air",
    "pred_action": "air"
  },
  "162392": {
    "x": 846.0,
    "y": 324.0,
    "visible": true,
    "action": "air",
    "pred_action": "air"
  },
  "162393": {
    "x": 841.0,
    "y": 329.0,
    "visible": true,
    "action": "air",
    "pred_action": "air"
  },
  "162394": {
    "x": 833.0,
    "y": 336.0,
    "visible": true,
    "action": "air",
    "pred_action": "air"
  },
  "162395": {
    "x": 828.0,
    "y": 343.0,
    "visible": true,
    "action": "air",
    "pred_action": "air"
  },
  "162396": {
    "x": 822.0,
    "y": 350.0,
    "visible": true,
    "action": "air",
    "pred_action": "air"
  },
  "162397": {
    "x": 817.0,
    "y": 358.0,
    "visible": true,
    "action": "air",
    "pred_action": "air"
  },
  "162398": {
    "x": 813.0,
    "y": 366.0,
    "visible": true,
    "action": "air",
    "pred_action": "air"
  },
  "162399": {
    "x": 804.0,
    "y": 373.0,
    "visible": true,
    "action": "air",
    "pred_action": "air"
  },
  "162400": {
    "x": 798.0,
    "y": 382.0,
    "visible": true,
    "action": "air",
    "pred_action": "air"
  },
  "162401": {
    "x": 791.0,
    "y": 389.0,
    "visible": true,
    "action": "air",
    "pred_action": "air"
  },
  "162402": {
    "x": 786.0,
    "y": 397.0,
    "visible": true,
    "action": "air",
    "pred_action": "air"
  },
  "162403": {
    "x": 782.0,
    "y": 407.0,
    "visible": true,
    "action": "air",
    "pred_action": "air"
  },
  "162404": {
    "x": 774.0,
    "y": 417.0,
    "visible": true,
    "action": "air",
    "pred_action": "air"
  },
  "162405": {
    "x": 767.0,
    "y": 425.0,
    "visible": true,
    "action": "air",
    "pred_action": "air"
  },
  "162406": {
    "x": 762.0,
    "y": 436.0,
    "visible": true,
    "action": "air",
    "pred_action": "air"
  },
  "162407": {
    "x": 754.0,
    "y": 447.0,
    "visible": true,
    "action": "air",
    "pred_action": "air"
  },
  "162408": {
    "x": 751.0,
    "y": 453.0,
    "visible": true,
    "action": "air",
    "pred_action": "air"
  },
  "162409": {
    "x": 741.0,
    "y": 466.0,
    "visible": true,
    "action": "air",
    "pred_action": "air"
  },
  "162410": {
    "x": 734.0,
    "y": 478.0,
    "visible": true,
    "action": "air",
    "pred_action": "air"
  },
  "162411": {
    "x": 729.0,
    "y": 490.0,
    "visible": true,
    "action": "air",
    "pred_action": "air"
  },
  "162412": {
    "x": 723.0,
    "y": 503.0,
    "visible": true,
    "action": "air",
    "pred_action": "air"
  },
  "162413": {
    "x": 714.0,
    "y": 515.0,
    "visible": true,
    "action": "air",
    "pred_action": "air"
  },
  "162414": {
    "x": 709.0,
    "y": 526.0,
    "visible": true,
    "action": "air",
    "pred_action": "air"
  },
  "162415": {
    "x": 702.0,
    "y": 538.0,
    "visible": true,
    "action": "air",
    "pred_action": "air"
  },
  "162416": {
    "x": 695.0,
    "y": 553.0,
    "visible": true,
    "action": "air",
    "pred_action": "air"
  },
  "162417": {
    "x": 691.0,
    "y": 565.0,
    "visible": true,
    "action": "air",
    "pred_action": "air"
  },
  "162418": {
    "x": 682.0,
    "y": 579.0,
    "visible": true,
    "action": "air",
    "pred_action": "air"
  },
  "162419": {
    "x": 676.0,
    "y": 592.0,
    "visible": true,
    "action": "air",
    "pred_action": "air"
  },
  "162420": {
    "x": 669.0,
    "y": 606.0,
    "visible": true,
    "action": "air",
    "pred_action": "air"
  },
  "162421": {
    "x": 661.4801980198018,
    "y": 615.6386138613859,
    "visible": true,
    "action": "bounce",
    "pred_action": "bounce"
  },
  "162422": {
    "x": 657.0,
    "y": 607.0,
    "visible": true,
    "action": "air",
    "pred_action": "air"
  },
  "162423": {
    "x": 655.0,
    "y": 602.0,
    "visible": true,
    "action": "air",
    "pred_action": "air"
  },
  "162424": {
    "x": 654.0,
    "y": 596.0,
    "visible": true,
    "action": "air",
    "pred_action": "air"
  },
  "162425": {
    "x": 651.0,
    "y": 590.0,
    "visible": true,
    "action": "air",
    "pred_action": "air"
  },
  "162426": {
    "x": 649.0,
    "y": 585.0,
    "visible": true,
    "action": "air",
    "pred_action": "air"
  },
  "162427": {
    "x": 645.0,
    "y": 581.0,
    "visible": true,
    "action": "air",
    "pred_action": "air"
  },
  "162428": {
    "x": 642.0,
    "y": 576.0,
    "visible": true,
    "action": "air",
    "pred_action": "air"
  },
  "162429": {
    "x": 641.0,
    "y": 571.0,
    "visible": true,
    "action": "air",
    "pred_action": "air"
  },
  "162430": {
    "x": 638.0,
    "y": 568.0,
    "visible": true,
    "action": "air",
    "pred_action": "air"
  },
  "162431": {
    "x": 634.0,
    "y": 565.0,
    "visible": true,
    "action": "air",
    "pred_action": "air"
  },
  "162432": {
    "x": 632.0,
    "y": 562.0,
    "visible": true,
    "action": "air",
    "pred_action": "air"
  },
  "162433": {
    "x": 626.0,
    "y": 560.0,
    "visible": true,
    "action": "air",
    "pred_action": "air"
  },
  "162434": {
    "x": 623.0,
    "y": 556.0,
    "visible": true,
    "action": "air",
    "pred_action": "air"
  },
  "162435": {
    "x": 621.0,
    "y": 556.0,
    "visible": true,
    "action": "air",
    "pred_action": "air"
  },
  "162436": {
    "x": 617.0,
    "y": 553.0,
    "visible": true,
    "action": "air",
    "pred_action": "air"
  },
  "162437": {
    "x": 614.0,
    "y": 552.0,
    "visible": true,
    "action": "air",
    "pred_action": "air"
  },
  "162438": {
    "x": 615.0,
    "y": 552.0,
    "visible": true,
    "action": "air",
    "pred_action": "air"
  },
  "162439": {
    "x": 611.0,
    "y": 552.0,
    "visible": true,
    "action": "air",
    "pred_action": "air"
  },
  "162440": {
    "x": 609.0,
    "y": 552.0,
    "visible": true,
    "action": "air",
    "pred_action": "air"
  },
  "162441": {
    "x": 606.0,
    "y": 550.0,
    "visible": true,
    "action": "air",
    "pred_action": "air"
  },
  "162442": {
    "x": 604.0,
    "y": 551.0,
    "visible": true,
    "action": "air",
    "pred_action": "air"
  },
  "162443": {
    "x": 595.0,
    "y": 553.0,
    "visible": true,
    "action": "air",
    "pred_action": "air"
  },
  "162444": {
    "x": 594.0,
    "y": 552.0,
    "visible": true,
    "action": "air",
    "pred_action": "air"
  },
  "162445": {
    "x": 591.0,
    "y": 555.0,
    "visible": true,
    "action": "air",
    "pred_action": "air"
  },
  "162446": {
    "x": 589.0,
    "y": 557.0,
    "visible": true,
    "action": "air",
    "pred_action": "air"
  },
  "162447": {
    "x": 587.0,
    "y": 559.0,
    "visible": true,
    "action": "air",
    "pred_action": "air"
  },
  "162448": {
    "x": 584.0,
    "y": 562.0,
    "visible": true,
    "action": "air",
    "pred_action": "air"
  },
  "162449": {
    "x": 581.0,
    "y": 565.0,
    "visible": true,
    "action": "air",
    "pred_action": "air"
  },
  "162450": {
    "x": 579.0,
    "y": 569.0,
    "visible": true,
    "action": "air",
    "pred_action": "air"
  },
  "162451": {
    "x": 576.5,
    "y": 572.0,
    "visible": false,
    "action": "air",
    "pred_action": "air"
  },
  "162452": {
    "x": 574.0,
    "y": 575.0,
    "visible": true,
    "action": "air",
    "pred_action": "air"
  },
  "162453": {
    "x": 569.8960396039603,
    "y": 576.0346534653463,
    "visible": true,
    "action": "hit",
    "pred_action": "air"
  },
  "162454": {
    "x": 578.2640264026402,
    "y": 562.0231023102309,
    "visible": false,
    "action": "air",
    "pred_action": "air"
  },
  "162455": {
    "x": 586.6320132013201,
    "y": 548.0115511551154,
    "visible": false,
    "action": "air",
    "pred_action": "air"
  },
  "162456": {
    "x": 595.0,
    "y": 534.0,
    "visible": true,
    "action": "air",
    "pred_action": "air"
  },
  "162457": {
    "x": 603.3333333333334,
    "y": 516.6666666666666,
    "visible": false,
    "action": "air",
    "pred_action": "air"
  },
  "162458": {
    "x": 611.6666666666666,
    "y": 499.3333333333333,
    "visible": false,
    "action": "air",
    "pred_action": "air"
  },
  "162459": {
    "x": 620.0,
    "y": 482.0,
    "visible": true,
    "action": "air",
    "pred_action": "air"
  },
  "162460": {
    "x": 625.0,
    "y": 469.0,
    "visible": true,
    "action": "air",
    "pred_action": "air"
  },
  "162461": {
    "x": 634.0,
    "y": 460.0,
    "visible": true,
    "action": "air",
    "pred_action": "air"
  },
  "162462": {
    "x": 641.0,
    "y": 446.0,
    "visible": true,
    "action": "air",
    "pred_action": "air"
  },
  "162463": {
    "x": 649.0,
    "y": 436.0,
    "visible": true,
    "action": "air",
    "pred_action": "air"
  },
  "162464": {
    "x": 654.0,
    "y": 426.0,
    "visible": true,
    "action": "air",
    "pred_action": "air"
  },
  "162465": {
    "x": 663.0,
    "y": 416.0,
    "visible": true,
    "action": "air",
    "pred_action": "air"
  },
  "162466": {
    "x": 669.0,
    "y": 408.0,
    "visible": true,
    "action": "air",
    "pred_action": "air"
  },
  "162467": {
    "x": 675.0,
    "y": 401.0,
    "visible": true,
    "action": "air",
    "pred_action": "air"
  },
  "162468": {
    "x": 682.0,
    "y": 394.0,
    "visible": true,
    "action": "air",
    "pred_action": "air"
  },
  "162469": {
    "x": 684.0,
    "y": 388.0,
    "visible": true,
    "action": "air",
    "pred_action": "air"
  },
  "162470": {
    "x": 687.0,
    "y": 382.0,
    "visible": true,
    "action": "air",
    "pred_action": "air"
  },
  "162471": {
    "x": 696.0,
    "y": 376.0,
    "visible": true,
    "action": "air",
    "pred_action": "air"
  },
  "162472": {
    "x": 702.0,
    "y": 371.0,
    "visible": true,
    "action": "air",
    "pred_action": "air"
  },
  "162473": {
    "x": 709.0,
    "y": 367.0,
    "visible": true,
    "action": "air",
    "pred_action": "air"
  },
  "162474": {
    "x": 712.0,
    "y": 363.0,
    "visible": true,
    "action": "air",
    "pred_action": "air"
  },
  "162475": {
    "x": 716.0,
    "y": 361.0,
    "visible": true,
    "action": "air",
    "pred_action": "air"
  },
  "162476": {
    "x": 723.0,
    "y": 357.0,
    "visible": true,
    "action": "air",
    "pred_action": "air"
  },
  "162477": {
    "x": 727.0,
    "y": 355.0,
    "visible": true,
    "action": "air",
    "pred_action": "air"
  },
  "162478": {
    "x": 733.0,
    "y": 354.0,
    "visible": true,
    "action": "air",
    "pred_action": "air"
  },
  "162479": {
    "x": 739.0,
    "y": 352.0,
    "visible": true,
    "action": "air",
    "pred_action": "air"
  },
  "162480": {
    "x": 740.0,
    "y": 350.0,
    "visible": true,
    "action": "air",
    "pred_action": "air"
  },
  "162481": {
    "x": 744.0,
    "y": 350.0,
    "visible": true,
    "action": "air",
    "pred_action": "air"
  },
  "162482": {
    "x": 747.0,
    "y": 351.0,
    "visible": true,
    "action": "air",
    "pred_action": "air"
  },
  "162483": {
    "x": 753.0,
    "y": 349.0,
    "visible": true,
    "action": "air",
    "pred_action": "air"
  },
  "162484": {
    "x": 757.0,
    "y": 350.0,
    "visible": true,
    "action": "air",
    "pred_action": "air"
  },
  "162485": {
    "x": 762.0,
    "y": 352.0,
    "visible": true,
    "action": "air",
    "pred_action": "air"
  },
  "162486": {
    "x": 764.0,
    "y": 352.0,
    "visible": true,
    "action": "air",
    "pred_action": "air"
  },
  "162487": {
    "x": 769.0,
    "y": 353.0,
    "visible": true,
    "action": "air",
    "pred_action": "air"
  },
  "162488": {
    "x": 772.3514851485148,
    "y": 355.56270627062696,
    "visible": false,
    "action": "air",
    "pred_action": "air"
  },
  "162489": {
    "x": 775.7029702970297,
    "y": 358.125412541254,
    "visible": false,
    "action": "air",
    "pred_action": "air"
  },
  "162490": {
    "x": 779.0544554455445,
    "y": 360.68811881188094,
    "visible": true,
    "action": "bounce",
    "pred_action": "bounce"
  },
  "162491": {
    "x": 783.0,
    "y": 356.0,
    "visible": true,
    "action": "air",
    "pred_action": "air"
  },
  "162492": {
    "x": 784.0,
    "y": 347.0,
    "visible": true,
    "action": "air",
    "pred_action": "air"
  },
  "162493": {
    "x": 786.0,
    "y": 339.0,
    "visible": true,
    "action": "air",
    "pred_action": "air"
  },
  "162494": {
    "x": 788.0,
    "y": 329.0,
    "visible": true,
    "action": "air",
    "pred_action": "air"
  },
  "162495": {
    "x": 789.0,
    "y": 322.0,
    "visible": true,
    "action": "air",
    "pred_action": "air"
  },
  "162496": {
    "x": 791.0,
    "y": 314.0,
    "visible": true,
    "action": "air",
    "pred_action": "air"
  },
  "162497": {
    "x": 793.0,
    "y": 305.0,
    "visible": true,
    "action": "air",
    "pred_action": "air"
  },
  "162498": {
    "x": 794.0,
    "y": 299.0,
    "visible": true,
    "action": "air",
    "pred_action": "air"
  },
  "162499": {
    "x": 798.0,
    "y": 293.0,
    "visible": true,
    "action": "air",
    "pred_action": "air"
  },
  "162500": {
    "x": 799.0,
    "y": 287.0,
    "visible": true,
    "action": "air",
    "pred_action": "air"
  },
  "162501": {
    "x": 798.539603960396,
    "y": 279.7970297029702,
    "visible": false,
    "action": "air",
    "pred_action": "air"
  },
  "162502": {
    "x": 798.079207920792,
    "y": 272.5940594059404,
    "visible": false,
    "action": "air",
    "pred_action": "air"
  },
  "162503": {
    "x": 797.618811881188,
    "y": 265.3910891089106,
    "visible": true,
    "action": "hit",
    "pred_action": "hit"
  },
  "162504": {
    "x": 790.0,
    "y": 264.0,
    "visible": true,
    "action": "air",
    "pred_action": "air"
  },
  "162505": {
    "x": 776.0,
    "y": 263.0,
    "visible": true,
    "action": "air",
    "pred_action": "air"
  },
  "162506": {
    "x": 766.0,
    "y": 258.0,
    "visible": true,
    "action": "air",
    "pred_action": "air"
  },
  "162507": {
    "x": 754.0,
    "y": 255.0,
    "visible": false,
    "action": "air",
    "pred_action": "air"
  },
  "162508": {
    "x": 742.0,
    "y": 252.0,
    "visible": false,
    "action": "air",
    "pred_action": "air"
  },
  "162509": {
    "x": 730.0,
    "y": 249.0,
    "visible": true,
    "action": "air",
    "pred_action": "air"
  },
  "162510": {
    "x": 716.0,
    "y": 243.0,
    "visible": true,
    "action": "air",
    "pred_action": "air"
  },
  "162511": {
    "x": 703.0,
    "y": 238.0,
    "visible": true,
    "action": "air",
    "pred_action": "air"
  },
  "162512": {
    "x": 687.0,
    "y": 236.0,
    "visible": true,
    "action": "air",
    "pred_action": "air"
  },
  "162513": {
    "x": 681.0,
    "y": 235.0,
    "visible": true,
    "action": "air",
    "pred_action": "air"
  },
  "162514": {
    "x": 668.0,
    "y": 233.0,
    "visible": true,
    "action": "air",
    "pred_action": "air"
  },
  "162515": {
    "x": 652.0,
    "y": 232.0,
    "visible": true,
    "action": "air",
    "pred_action": "air"
  },
  "162516": {
    "x": 643.0,
    "y": 230.0,
    "visible": true,
    "action": "air",
    "pred_action": "air"
  },
  "162517": {
    "x": 626.0,
    "y": 230.0,
    "visible": true,
    "action": "air",
    "pred_action": "air"
  },
  "162518": {
    "x": 613.0,
    "y": 230.0,
    "visible": true,
    "action": "air",
    "pred_action": "air"
  },
  "162519": {
    "x": 604.0,
    "y": 229.0,
    "visible": true,
    "action": "air",
    "pred_action": "air"
  },
  "162520": {
    "x": 589.0,
    "y": 230.0,
    "visible": true,
    "action": "air",
    "pred_action": "air"
  },
  "162521": {
    "x": 567.0,
    "y": 232.0,
    "visible": true,
    "action": "air",
    "pred_action": "air"
  },
  "162522": {
    "x": 562.0,
    "y": 230.0,
    "visible": true,
    "action": "air",
    "pred_action": "air"
  },
  "162523": {
    "x": 547.0,
    "y": 233.0,
    "visible": true,
    "action": "air",
    "pred_action": "air"
  },
  "162524": {
    "x": 530.0,
    "y": 235.0,
    "visible": true,
    "action": "air",
    "pred_action": "air"
  },
  "162525": {
    "x": 519.0,
    "y": 236.0,
    "visible": true,
    "action": "air",
    "pred_action": "air"
  },
  "162526": {
    "x": 504.0,
    "y": 238.0,
    "visible": true,
    "action": "air",
    "pred_action": "air"
  },
  "162527": {
    "x": 488.0,
    "y": 243.0,
    "visible": true,
    "action": "air",
    "pred_action": "air"
  },
  "162528": {
    "x": 473.0,
    "y": 246.33333333333334,
    "visible": false,
    "action": "air",
    "pred_action": "air"
  },
  "162529": {
    "x": 458.0,
    "y": 249.66666666666666,
    "visible": false,
    "action": "air",
    "pred_action": "air"
  },
  "162530": {
    "x": 443.0,
    "y": 253.0,
    "visible": true,
    "action": "air",
    "pred_action": "air"
  },
  "162531": {
    "x": 433.0,
    "y": 256.0,
    "visible": true,
    "action": "air",
    "pred_action": "air"
  },
  "162532": {
    "x": 414.0,
    "y": 262.0,
    "visible": true,
    "action": "air",
    "pred_action": "air"
  },
  "162533": {
    "x": 399.0,
    "y": 267.0,
    "visible": true,
    "action": "air",
    "pred_action": "air"
  },
  "162534": {
    "x": 744.0,
    "y": 550.0,
    "visible": true,
    "action": "air",
    "pred_action": "air"
  },
  "162535": {
    "x": 748.6666666666666,
    "y": 548.6666666666666,
    "visible": false,
    "action": "air",
    "pred_action": "air"
  },
  "162536": {
    "x": 753.3333333333334,
    "y": 547.3333333333334,
    "visible": false,
    "action": "air",
    "pred_action": "air"
  },
  "162537": {
    "x": 758.0,
    "y": 546.0,
    "visible": true,
    "action": "air",
    "pred_action": "air"
  },
  "162538": {
    "x": 764.0,
    "y": 545.6666666666666,
    "visible": false,
    "action": "air",
    "pred_action": "air"
  },
  "162539": {
    "x": 770.0,
    "y": 545.3333333333334,
    "visible": false,
    "action": "air",
    "pred_action": "air"
  },
  "162540": {
    "x": 776.0,
    "y": 545.0,
    "visible": true,
    "action": "air",
    "pred_action": "air"
  },
  "162541": {
    "x": 596.3333333333334,
    "y": 477.6666666666667,
    "visible": false,
    "action": "air",
    "pred_action": "air"
  },
  "162542": {
    "x": 416.6666666666667,
    "y": 410.33333333333337,
    "visible": false,
    "action": "air",
    "pred_action": "air"
  },
  "162543": {
    "x": 237.0,
    "y": 343.0,
    "visible": true,
    "action": "air",
    "pred_action": "air"
  },
  "162544": {
    "x": 222.0,
    "y": 353.0,
    "visible": true,
    "action": "air",
    "pred_action": "air"
  },
  "162545": {
    "x": 203.0,
    "y": 364.0,
    "visible": true,
    "action": "air",
    "pred_action": "air"
  },
  "162546": {
    "x": 190.0,
    "y": 374.0,
    "visible": true,
    "action": "air",
    "pred_action": "air"
  },
  "162547": {
    "x": 172.0,
    "y": 386.0,
    "visible": true,
    "action": "air",
    "pred_action": "air"
  },
  "162548": {
    "x": 153.0,
    "y": 401.0,
    "visible": true,
    "action": "air",
    "pred_action": "air"
  },
  "162549": {
    "x": 137.0,
    "y": 410.0,
    "visible": true,
    "action": "air",
    "pred_action": "air"
  },
  "162550": {
    "x": 115.0,
    "y": 423.0,
    "visible": true,
    "action": "air",
    "pred_action": "air"
  },
  "162551": {
    "x": 105.0,
    "y": 432.0,
    "visible": true,
    "action": "air",
    "pred_action": "air"
  },
  "162552": {
    "x": 86.5,
    "y": 448.0,
    "visible": false,
    "action": "air",
    "pred_action": "air"
  },
  "162553": {
    "x": 68.0,
    "y": 464.0,
    "visible": true,
    "action": "air",
    "pred_action": "air"
  },
  "162554": {
    "x": 44.0,
    "y": 482.0,
    "visible": true,
    "action": "air",
    "pred_action": "air"
  },
  "162555": {
    "x": 138.44444444444446,
    "y": 487.0,
    "visible": false,
    "action": "air",
    "pred_action": "air"
  },
  "162556": {
    "x": 232.88888888888889,
    "y": 492.0,
    "visible": false,
    "action": "air",
    "pred_action": "air"
  },
  "162557": {
    "x": 327.3333333333333,
    "y": 497.0,
    "visible": false,
    "action": "air",
    "pred_action": "air"
  },
  "162558": {
    "x": 421.77777777777777,
    "y": 502.0,
    "visible": false,
    "action": "air",
    "pred_action": "air"
  },
  "162559": {
    "x": 516.2222222222222,
    "y": 507.0,
    "visible": false,
    "action": "air",
    "pred_action": "air"
  },
  "162560": {
    "x": 610.6666666666666,
    "y": 512.0,
    "visible": false,
    "action": "air",
    "pred_action": "air"
  },
  "162561": {
    "x": 705.1111111111111,
    "y": 517.0,
    "visible": false,
    "action": "air",
    "pred_action": "air"
  },
  "162562": {
    "x": 799.5555555555555,
    "y": 522.0,
    "visible": false,
    "action": "air",
    "pred_action": "air"
  },
  "162563": {
    "x": 894.0,
    "y": 527.0,
    "visible": true,
    "action": "air",
    "pred_action": "air"
  },
  "162564": {
    "x": 893.75,
    "y": 528.75,
    "visible": false,
    "action": "air",
    "pred_action": "air"
  },
  "162565": {
    "x": 893.5,
    "y": 530.5,
    "visible": false,
    "action": "air",
    "pred_action": "air"
  },
  "162566": {
    "x": 893.25,
    "y": 532.25,
    "visible": false,
    "action": "air",
    "pred_action": "air"
  },
  "162567": {
    "x": 893.0,
    "y": 534.0,
    "visible": true,
    "action": "air",
    "pred_action": "air"
  },
  "162568": {
    "x": 819.9166666666666,
    "y": 551.5833333333334,
    "visible": false,
    "action": "air",
    "pred_action": "air"
  },
  "162569": {
    "x": 746.8333333333334,
    "y": 569.1666666666666,
    "visible": false,
    "action": "air",
    "pred_action": "air"
  },
  "162570": {
    "x": 673.75,
    "y": 586.75,
    "visible": false,
    "action": "air",
    "pred_action": "air"
  },
  "162571": {
    "x": 600.6666666666667,
    "y": 604.3333333333334,
    "visible": false,
    "action": "air",
    "pred_action": "air"
  },
  "162572": {
    "x": 527.5833333333334,
    "y": 621.9166666666666,
    "visible": false,
    "action": "air",
    "pred_action": "air"
  },
  "162573": {
    "x": 454.5,
    "y": 639.5,
    "visible": false,
    "action": "air",
    "pred_action": "air"
  },
  "162574": {
    "x": 381.4166666666667,
    "y": 657.0833333333334,
    "visible": false,
    "action": "air",
    "pred_action": "air"
  },
  "162575": {
    "x": 308.33333333333337,
    "y": 674.6666666666666,
    "visible": false,
    "action": "air",
    "pred_action": "air"
  },
  "162576": {
    "x": 235.25,
    "y": 692.25,
    "visible": false,
    "action": "air",
    "pred_action": "air"
  },
  "162577": {
    "x": 162.16666666666674,
    "y": 709.8333333333333,
    "visible": false,
    "action": "air",
    "pred_action": "air"
  },
  "162578": {
    "x": 89.08333333333337,
    "y": 727.4166666666666,
    "visible": false,
    "action": "air",
    "pred_action": "air"
  },
  "162579": {
    "x": 16.0,
    "y": 745.0,
    "visible": true,
    "action": "air",
    "pred_action": "air"
  },
  "162580": {
    "x": 20.0,
    "y": 747.0,
    "visible": true,
    "action": "air",
    "pred_action": "air"
  },
  "162581": {
    "x": 25.0,
    "y": 747.0,
    "visible": true,
    "action": "air",
    "pred_action": "air"
  },
  "162582": {
    "x": 32.0,
    "y": 746.0,
    "visible": true,
    "action": "air",
    "pred_action": "air"
  },
  "162583": {
    "x": 40.0,
    "y": 747.0,
    "visible": true,
    "action": "air",
    "pred_action": "air"
  },
  "162584": {
    "x": 50.0,
    "y": 748.0,
    "visible": true,
    "action": "air",
    "pred_action": "air"
  },
  "162585": {
    "x": 53.0,
    "y": 748.0,
    "visible": true,
    "action": "air",
    "pred_action": "air"
  },
  "162586": {
    "x": 63.0,
    "y": 752.0,
    "visible": true,
    "action": "air",
    "pred_action": "air"
  },
  "162587": {
    "x": 71.0,
    "y": 754.0,
    "visible": true,
    "action": "air",
    "pred_action": "air"
  },
  "162588": {
    "x": 75.0,
    "y": 756.0,
    "visible": true,
    "action": "air",
    "pred_action": "air"
  },
  "162589": {
    "x": 83.0,
    "y": 761.0,
    "visible": true,
    "action": "air",
    "pred_action": "air"
  },
  "162590": {
    "x": 93.0,
    "y": 765.0,
    "visible": true,
    "action": "air",
    "pred_action": "air"
  },
  "162591": {
    "x": 97.0,
    "y": 768.0,
    "visible": true,
    "action": "air",
    "pred_action": "air"
  },
  "162592": {
    "x": 105.0,
    "y": 773.0,
    "visible": true,
    "action": "air",
    "pred_action": "air"
  },
  "162593": {
    "x": 114.0,
    "y": 779.0,
    "visible": true,
    "action": "air",
    "pred_action": "air"
  },
  "162594": {
    "x": 116.0,
    "y": 783.0,
    "visible": true,
    "action": "air",
    "pred_action": "air"
  },
  "162595": {
    "x": 127.0,
    "y": 789.0,
    "visible": true,
    "action": "air",
    "pred_action": "air"
  },
  "162596": {
    "x": 135.0,
    "y": 797.0,
    "visible": true,
    "action": "air",
    "pred_action": "air"
  },
  "162597": {
    "x": 140.0,
    "y": 803.0,
    "visible": true,
    "action": "air",
    "pred_action": "air"
  },
  "162598": {
    "x": 148.0,
    "y": 811.0,
    "visible": true,
    "action": "air",
    "pred_action": "air"
  },
  "162599": {
    "x": 157.0,
    "y": 817.0,
    "visible": true,
    "action": "air",
    "pred_action": "air"
  },
  "162600": {
    "x": 161.0,
    "y": 817.0,
    "visible": true,
    "action": "air",
    "pred_action": "air"
  },
  "162601": {
    "x": 169.0,
    "y": 819.0,
    "visible": true,
    "action": "air",
    "pred_action": "air"
  },
  "162602": {
    "x": 176.0,
    "y": 821.0,
    "visible": true,
    "action": "air",
    "pred_action": "air"
  },
  "162603": {
    "x": 184.0,
    "y": 821.0,
    "visible": true,
    "action": "air",
    "pred_action": "air"
  },
  "162604": {
    "x": 191.0,
    "y": 824.0,
    "visible": true,
    "action": "air",
    "pred_action": "air"
  },
  "162605": {
    "x": 200.0,
    "y": 827.0,
    "visible": true,
    "action": "air",
    "pred_action": "air"
  },
  "162606": {
    "x": 203.0,
    "y": 828.0,
    "visible": true,
    "action": "air",
    "pred_action": "air"
  },
  "162607": {
    "x": 215.0,
    "y": 833.0,
    "visible": true,
    "action": "air",
    "pred_action": "air"
  },
  "162608": {
    "x": 222.0,
    "y": 837.0,
    "visible": true,
    "action": "air",
    "pred_action": "air"
  },
  "162609": {
    "x": 227.0,
    "y": 839.0,
    "visible": true,
    "action": "air",
    "pred_action": "air"
  },
  "162610": {
    "x": 234.0,
    "y": 847.0,
    "visible": true,
    "action": "air",
    "pred_action": "air"
  },
  "162611": {
    "x": 244.0,
    "y": 853.0,
    "visible": true,
    "action": "air",
    "pred_action": "air"
  },
  "162612": {
    "x": 249.0,
    "y": 857.0,
    "visible": true,
    "action": "air",
    "pred_action": "air"
  },
  "162613": {
    "x": 258.0,
    "y": 864.0,
    "visible": true,
    "action": "air",
    "pred_action": "air"
  },
  "162614": {
    "x": 264.0,
    "y": 872.0,
    "visible": true,
    "action": "air",
    "pred_action": "air"
  },
  "162615": {
    "x": 270.0,
    "y": 876.0,
    "visible": true,
    "action": "air",
    "pred_action": "air"
  },
  "162616": {
    "x": 280.0,
    "y": 880.0,
    "visible": true,
    "action": "air",
    "pred_action": "air"
  },
  "162617": {
    "x": 288.0,
    "y": 882.0,
    "visible": true,
    "action": "air",
    "pred_action": "air"
  },
  "162618": {
    "x": 291.0,
    "y": 883.0,
    "visible": true,
    "action": "air",
    "pred_action": "air"
  },
  "162619": {
    "x": 303.0,
    "y": 886.0,
    "visible": true,
    "action": "air",
    "pred_action": "air"
  },
  "162620": {
    "x": 311.0,
    "y": 889.0,
    "visible": true,
    "action": "air",
    "pred_action": "air"
  },
  "162621": {
    "x": 314.0,
    "y": 890.0,
    "visible": true,
    "action": "air",
    "pred_action": "air"
  },
  "162622": {
    "x": 322.0,
    "y": 894.0,
    "visible": true,
    "action": "air",
    "pred_action": "air"
  },
  "162623": {
    "x": 332.0,
    "y": 901.0,
    "visible": true,
    "action": "air",
    "pred_action": "air"
  },
  "162624": {
    "x": 337.0,
    "y": 903.0,
    "visible": true,
    "action": "air",
    "pred_action": "air"
  },
  "162625": {
    "x": 344.0,
    "y": 907.0,
    "visible": true,
    "action": "air",
    "pred_action": "air"
  },
  "162626": {
    "x": 352.0,
    "y": 915.0,
    "visible": true,
    "action": "air",
    "pred_action": "air"
  },
  "162627": {
    "x": 355.0,
    "y": 918.0,
    "visible": true,
    "action": "air",
    "pred_action": "air"
  },
  "162628": {
    "x": 367.0,
    "y": 926.0,
    "visible": true,
    "action": "air",
    "pred_action": "air"
  },
  "162629": {
    "x": 374.0,
    "y": 934.0,
    "visible": true,
    "action": "air",
    "pred_action": "air"
  },
  "162630": {
    "x": 378.0,
    "y": 939.0,
    "visible": true,
    "action": "air",
    "pred_action": "air"
  },
  "162631": {
    "x": 385.0,
    "y": 941.0,
    "visible": true,
    "action": "air",
    "pred_action": "air"
  },
  "162632": {
    "x": 396.0,
    "y": 944.0,
    "visible": true,
    "action": "air",
    "pred_action": "air"
  },
  "162633": {
    "x": 400.0,
    "y": 944.0,
    "visible": true,
    "action": "air",
    "pred_action": "air"
  },
  "162634": {
    "x": 409.0,
    "y": 947.0,
    "visible": true,
    "action": "air",
    "pred_action": "air"
  },
  "162635": {
    "x": 415.0,
    "y": 951.0,
    "visible": true,
    "action": "air",
    "pred_action": "air"
  },
  "162636": {
    "x": 423.0,
    "y": 953.0,
    "visible": true,
    "action": "air",
    "pred_action": "air"
  },
  "162637": {
    "x": 430.0,
    "y": 958.0,
    "visible": true,
    "action": "air",
    "pred_action": "air"
  },
  "162638": {
    "x": 439.0,
    "y": 964.0,
    "visible": true,
    "action": "air",
    "pred_action": "air"
  },
  "162639": {
    "x": 443.0,
    "y": 966.0,
    "visible": true,
    "action": "air",
    "pred_action": "air"
  },
  "162640": {
    "x": 453.0,
    "y": 972.0,
    "visible": true,
    "action": "air",
    "pred_action": "air"
  },
  "162641": {
    "x": 460.0,
    "y": 980.0,
    "visible": true,
    "action": "air",
    "pred_action": "air"
  },
  "162642": {
    "x": 465.0,
    "y": 985.0,
    "visible": true,
    "action": "air",
    "pred_action": "air"
  },
  "162643": {
    "x": 472.0,
    "y": 992.0,
    "visible": true,
    "action": "air",
    "pred_action": "air"
  },
  "162644": {
    "x": 483.0,
    "y": 999.0,
    "visible": true,
    "action": "air",
    "pred_action": "air"
  },
  "162645": {
    "x": 486.0,
    "y": 1000.0,
    "visible": true,
    "action": "air",
    "pred_action": "air"
  },
  "162646": {
    "x": 493.0,
    "y": 1002.0,
    "visible": true,
    "action": "air",
    "pred_action": "air"
  },
  "162647": {
    "x": 501.0,
    "y": 1005.0,
    "visible": true,
    "action": "air",
    "pred_action": "air"
  },
  "162648": {
    "x": 505.0,
    "y": 1005.0,
    "visible": true,
    "action": "air",
    "pred_action": "air"
  }
}